LICENSE
MANIFEST.in
README.rst
pavement.py
requirements-dev.txt
requirements.txt
setup.py
tox.ini
docs/Makefile
docs/make.bat
docs/source/README
docs/source/commandline.rst
docs/source/conf.py
docs/source/index.rst
docs/source/install.rst
docs/source/output.rst
docs/source/searchguide.rst
docs/source/_static/.gitkeep
tests/test_pattern.py
weihnachtsgurke.egg-info/PKG-INFO
weihnachtsgurke.egg-info/SOURCES.txt
weihnachtsgurke.egg-info/dependency_links.txt
weihnachtsgurke.egg-info/entry_points.txt
weihnachtsgurke.egg-info/not-zip-safe
weihnachtsgurke.egg-info/pbr.json
weihnachtsgurke.egg-info/requires.txt
weihnachtsgurke.egg-info/top_level.txt
wng/__init__.py
wng/cmdline.py
wng/corpus_metadata.py
wng/html.py
wng/metadata.py
wng/pattern.py
wng/util.py