Metadata-Version: 1.1
Name: weihnachtsgurke
Version: 0.3
Summary: A program for searching for strings of text in the PYCCLE-TCP corpus
Home-page: https://weihnachtsgurke.readthedocs.io/en/latest/
Author: Aaron Ecay
Author-email: aaronecay@gmail.com
License: UNKNOWN
Platform: UNKNOWN
Classifier: Development Status :: 3 - Alpha
Classifier: Environment :: Console
Classifier: License :: OSI Approved :: GNU General Public License v3 or later (GPLv3+)
Classifier: Natural Language :: English
Classifier: Operating System :: OS Independent
Classifier: Programming Language :: Python :: 2.6
Classifier: Programming Language :: Python :: 2.7
Classifier: Programming Language :: Python :: 3.3
Classifier: Programming Language :: Python :: Implementation :: PyPy
Classifier: Topic :: Other/Nonlisted Topic
